mobfot/__init__.py
mobfot/client.py
mobfot-1.4.0.dist-info/LICENSE
mobfot-1.4.0.dist-info/METADATA
mobfot-1.4.0.dist-info/WHEEL
mobfot-1.4.0.dist-info/top_level.txt
mobfot-1.4.0.dist-info/RECORD
