Metadata-Version: 2.1
Name: mobfot
Version: 1.4.0
Summary: An unofficial Python client for the FotMob API
Author: Brian Greenwood
License: MIT
Project-URL: homepage, https://bgrnwd.com/mobfot/
Project-URL: repository, https://github.com/bgrnwd/mobfot
Keywords: fotmob,soccer,api,football
Classifier: Development Status :: 5 - Production/Stable
Classifier: Environment :: Console
Classifier: Intended Audience :: Developers
Classifier: License :: OSI Approved :: MIT License
Classifier: Operating System :: OS Independent
Classifier: Programming Language :: Python
Classifier: Programming Language :: Python :: 3 :: Only
Classifier: Programming Language :: Python :: 3.8
Classifier: Programming Language :: Python :: 3.9
Classifier: Programming Language :: Python :: 3.10
Classifier: Programming Language :: Python :: 3.11
Classifier: Programming Language :: Python :: 3.12
Classifier: Topic :: Software Development :: Libraries :: Python Modules
Requires-Python: >=3.7
License-File: LICENSE
Requires-Dist: requests >=2.31.0
Requires-Dist: CacheControl >=0.13.1
Provides-Extra: test
Requires-Dist: ruff ; extra == 'test'
Requires-Dist: behave ; extra == 'test'
Requires-Dist: mypy ; extra == 'test'
Requires-Dist: reformat-gherkin ; extra == 'test'
Requires-Dist: types-requests ; extra == 'test'
Requires-Dist: mkdocs ; extra == 'test'
Requires-Dist: mkdocstrings[python] ; extra == 'test'
Requires-Dist: mkdocs-material ; extra == 'test'
